jerboapy/__init__.py
jerboapy/jerboapy_bin.cpython-310-darwin.so
jerboapy/jerboapy_bin.cpython-311-darwin.so
jerboapy/jerboapy_bin.cpython-312-darwin.so
jerboapy/jerboapy_bin.cpython-313-darwin.so
jerboapy_ext/Color4.py
jerboapy_ext/Point3.py
jerboapy_ext/__init__.py
jerboapy_ext/potpourri
jerboapy_ext/render.py
jerboapy_ext/rules.py
jerboapy_ext/utils.py
jerboapy-0.2rc340.dist-info/METADATA
jerboapy-0.2rc340.dist-info/WHEEL
jerboapy-0.2rc340.dist-info/licenses/LICENSE
jerboapy-0.2rc340.dist-info/RECORD
