Metadata-Version: 2.4
Name: jerboapy
Version: 0.2rc340
Summary: Bindings C++ avec pybind11 de Jerboa
Author-Email: Hakim Belhaouari <hakim.belhaouari@univ-poitiers.fr>
License-Expression: GPL-3.0-or-later
Requires-Python: >=3.11
Provides-Extra: ext
Requires-Dist: pyvista[trame]; extra == "ext"
Requires-Dist: trame; extra == "ext"
Requires-Dist: numpy; extra == "ext"
Requires-Dist: tqdm; extra == "ext"
